MANIFEST.in
README.rst
requirements.txt
setup.py
tests/__init__.py
tests/test_cluster.py
tests/test_host.py
tests/fixtures/__init__.py
tests/fixtures/host.py
zookeeper_monitor/__init__.py
zookeeper_monitor/handlers.py
zookeeper_monitor/version.py
zookeeper_monitor/web.py
zookeeper_monitor.egg-info/PKG-INFO
zookeeper_monitor.egg-info/SOURCES.txt
zookeeper_monitor.egg-info/dependency_links.txt
zookeeper_monitor.egg-info/requires.txt
zookeeper_monitor.egg-info/top_level.txt
zookeeper_monitor/front/static/favicon.png
zookeeper_monitor/front/template/cluster.html
zookeeper_monitor/front/template/host.html
zookeeper_monitor/front/template/layout.html
zookeeper_monitor/zk/__init__.py
zookeeper_monitor/zk/cluster.py
zookeeper_monitor/zk/exceptions.py
zookeeper_monitor/zk/host.py