Metadata-Version: 1.1
Name: zookeeper-monitor
Version: 0.3.0
Summary: Zookeeper's four letters command wrapper and web monitor.
Home-page: https://github.com/kwarunek/zookeeper_monitor
Author: Krzysztof Warunek
Author-email: krzysztof@warunek.net
License: MIT
Keywords: zookeeper,tcp,tornado
Platform: UNKNOWN
Classifier: License :: OSI Approved :: MIT License
Classifier: Programming Language :: Python :: 2.7
Classifier: Programming Language :: Python :: 3
Classifier: Programming Language :: Python :: 3.0
Classifier: Programming Language :: Python :: 3.1
Classifier: Programming Language :: Python :: 3.2
Classifier: Programming Language :: Python :: 3.3
Classifier: Programming Language :: Python :: 3.4
Classifier: Operating System :: POSIX
Classifier: Development Status :: 4 - Beta
